beeper/__init__.py
beeper/chain.py
beeper/evm.py
beeper/util.py
beeper/solc/Token.abi
beeper/solc/pancake_factory_v3.abi
beeper/solc/pancake_pool_v3.abi
beeper/solc/pancake_position_v3.abi
beeper/solc/pancake_quoter_v3.abi
beeper/solc/pancake_swaprouter_v3.abi
beeper/solc/Beeper.sol/Beeper.json
beeper/solc/BeeperToken.sol/BeeperToken.json
beeper/solc/ERC20.sol/ERC20.json
beeper/solc/LpLockerv2.sol/LpLockerv2.json
beeper/solc/Util.sol/Util.json
beeper_python-0.1.2.dist-info/METADATA
beeper_python-0.1.2.dist-info/WHEEL
beeper_python-0.1.2.dist-info/top_level.txt
beeper_python-0.1.2.dist-info/RECORD
