Metadata-Version: 2.4
Name: beeper-python
Version: 0.1.2
Summary: python sdk for beeper operation
Requires-Python: >=3.10
Requires-Dist: web3>=7.10.0
Requires-Dist: python-dotenv>=1.1.0
Requires-Dist: requests>=2.26.0
Requires-Dist: pytest>=8.3.5
